mypaas/__init__.py
mypaas/__main__.py
mypaas/client/__init__.py
mypaas/client/_keys.py
mypaas/client/_push.py
mypaas/daemon/__init__.py
mypaas/daemon/__main__.py
mypaas/daemon/_api.py
mypaas/daemon/_statsgen.py
mypaas/server/__init__.py
mypaas/server/_auth.py
mypaas/server/_daemon.py
mypaas/server/_deploy.py
mypaas/server/_init.py
mypaas/server/_reboot.py
mypaas/server/_stats.py
mypaas/server/_traefik.py
mypaas/stats/__init__.py
mypaas/stats/__main__.py
mypaas/stats/client_code.py
mypaas/stats/client_style.py
mypaas/stats/collector.py
mypaas/stats/monitor.py
mypaas/stats/receiver.py
mypaas/stats/server.py
mypaas/utils/__init__.py
mypaas/utils/_crypto.py
mypaas/utils/_deploy_config.py
mypaas/utils/_utils.py
mypaas-0.5.9.dist-info/LICENSE
mypaas-0.5.9.dist-info/METADATA
mypaas-0.5.9.dist-info/WHEEL
mypaas-0.5.9.dist-info/entry_points.txt
mypaas-0.5.9.dist-info/top_level.txt
mypaas-0.5.9.dist-info/zip-safe
mypaas-0.5.9.dist-info/RECORD
