Metadata-Version: 2.1
Name: mypaas
Version: 0.5.9
Summary: Run your own PaaS using Docker, Traefik, and great monitoring
Home-page: https://github.com/almarklein/mypaas
Author: Almar Klein
Author-email: 
License: 2-clause BSD
Keywords: paas,saas,deployment,traefik,docker
Platform: any
Classifier: Development Status :: 4 - Beta
Classifier: Intended Audience :: Developers
Classifier: Topic :: Internet :: WWW/HTTP
Classifier: License :: OSI Approved :: BSD License
Classifier: Operating System :: MacOS :: MacOS X
Classifier: Operating System :: Microsoft :: Windows
Classifier: Operating System :: POSIX
Classifier: Programming Language :: Python
Classifier: Programming Language :: Python :: 3 :: Only
Classifier: Programming Language :: Python :: 3.6
Classifier: Programming Language :: Python :: 3.7
Classifier: Programming Language :: Python :: 3.8
Classifier: Programming Language :: Python :: 3.9
Classifier: Programming Language :: Python :: 3.10
Classifier: Programming Language :: Python :: 3.11
Requires-Python: >=3.6
License-File: LICENSE
Requires-Dist: cryptography
Requires-Dist: requests
Requires-Dist: pyperclip
Requires-Dist: toml
Provides-Extra: server
Requires-Dist: uvicorn ; extra == 'server'
Requires-Dist: asgineer ; extra == 'server'
Requires-Dist: psutil ; extra == 'server'
Requires-Dist: fastuaparser ; extra == 'server'
Requires-Dist: pscript ; extra == 'server'
